quantkit/__init__.py
quantkit/_version.py
quantkit/core.py
quantkit-0.0.1rc1.dist-info/METADATA
quantkit-0.0.1rc1.dist-info/WHEEL
quantkit-0.0.1rc1.dist-info/top_level.txt
quantkit-0.0.1rc1.dist-info/RECORD
